mrannotate/ImageLabeller.py
mrannotate/__init__.py
mrannotate-0.0.4.dist-info/METADATA
mrannotate-0.0.4.dist-info/WHEEL
mrannotate-0.0.4.dist-info/RECORD
